<?xml version="1.0" encoding="UTF-8" ?>
<NotepadPlus>
 <AutoComplete language="mpf spf def">
     <Environment ignoreCase="no" startFunc="(" stopFunc=")" paramSeparator="," terminal=""  additionalWordChar = ""/>
     <KeyWord name="SA_AA_OFF_LIMIT" />
     <KeyWord name="SA_MDB_WORKAREA_MINUS_ENABLE" />
     <KeyWord name="SA_MDB_WORKAREA_PLUS_ENABLE" />
     <KeyWord name="SA_MDD_SPIND_MAX_VELO_G26" />
     <KeyWord name="SA_MDD_SPIND_MAX_VELO_LIMS" />
     <KeyWord name="SA_MDD_SPIND_MIN_VELO_G25" />
     <KeyWord name="SA_MDD_WORKAREA_LIMIT_MINUS" />
     <KeyWord name="SA_MDD_WORKAREA_LIMIT_PLUS" />
     <KeyWord name="AC_AUTO_JOG_STATE" />
     <KeyWord name="AC_AUXFU_M_TICK" />
     <KeyWord name="AC_AUXFU_PREDEF_INDEX" />
     <KeyWord name="AC_AUXFU_SPEC" />
     <KeyWord name="AC_AUXFU_TICK" />
     <KeyWord name="AC_AUXFU_EXT" />
     <KeyWord name="AC_AUXFU_TYPE" />
     <KeyWord name="AC_AUXFU_VALUE" />
     <KeyWord name="AC_AUXFU_M_VALUE" />
     <KeyWord name="AA_CPACTFA" />
     <KeyWord name="AA_CPACTLA" />
     <KeyWord name="AA_CPBC" />
     <KeyWord name="AA_CPDEFLA" />
     <KeyWord name="AA_CPFACCT" />
     <KeyWord name="AA_CPFACT" />
     <KeyWord name="AA_CPFCMDPT" />
     <KeyWord name="AA_CPFCMDVT" />
     <KeyWord name="AA_CPFMOF" />
     <KeyWord name="AA_CPFMON" />
     <KeyWord name="AA_CPFMSON" />
     <KeyWord name="AA_CPFREQV" />
     <KeyWord name="AA_CPFRS" />
     <KeyWord name="AA_CPLACC" />
     <KeyWord name="AA_CPLCMDP" />
     <KeyWord name="AA_CPLCMDV" />
     <KeyWord name="AA_CPLCTID" />
     <KeyWord name="AA_CPLDEN" />
     <KeyWord name="AA_CPLINSC" />
     <KeyWord name="AA_CPLINTR" />
     <KeyWord name="AA_CPLNUM" />
     <KeyWord name="AA_CPLOUTSC" />
     <KeyWord name="AA_CPLOUTTR" />
     <KeyWord name="AA_CPLRS" />
     <KeyWord name="AA_CPLSETVAL" />
     <KeyWord name="AA_CPLSTATE" />
     <KeyWord name="AA_CPLTYPE" />
     <KeyWord name="AA_CPMALARM" />
     <KeyWord name="AA_CPMRESET" />
     <KeyWord name="AA_CPMSTART" />
     <KeyWord name="AA_CPMSTARTPRT" />
     <KeyWord name="AA_CPMVDI" />
     <KeyWord name="AA_CPNACTFA" />
     <KeyWord name="AA_CPNACTLA" />
     <KeyWord name="AA_CPNDEFLA" />
     <KeyWord name="AA_CPSETTYPE" />
     <KeyWord name="AA_CPSYNCOP" />
     <KeyWord name="AA_CPSYNCOP2" />
     <KeyWord name="AA_CPSYNCOV" />
     <KeyWord name="AA_CPSYNFIP" />
     <KeyWord name="AA_CPSYNFIP2" />
     <KeyWord name="AA_CPSYNFIV" />
     <KeyWord name="AC_IPO_BUF" />
     <KeyWord name="AC_CUTTING_TIME" />
     <KeyWord name="AC_CYCLE_TIME" />
     <KeyWord name="AC_OPERATING_TIME" />
     <KeyWord name="P_CHBFR" />
     <KeyWord name="AA_ETRANS" />
     <KeyWord name="P_GFR" />
     <KeyWord name="P_SETFR" />
     <KeyWord name="P_UIFR" />
     <KeyWord name="MC_AXCONF_CHANAX_NAME_TAB" />
     <KeyWord name="ON_COLLISION_MASK" />
     <KeyWord name="SC_PA_CENT_ABS" />
     <KeyWord name="SC_PA_CENT_ORD" />
     <KeyWord name="SC_PA_CONT_ABS" />
     <KeyWord name="SC_PA_CONT_ORD" />
     <KeyWord name="SC_PA_MINUS_LIM" />
     <KeyWord name="SC_PA_PLUS_LIM" />
     <KeyWord name="SC_PA_ACTIV_IMMED" />
     <KeyWord name="SC_PA_CONT_NUM" />
     <KeyWord name="SC_PA_CONT_TYP" />
     <KeyWord name="SC_PA_LIM_3DIM" />
     <KeyWord name="SC_PA_ORI" />
     <KeyWord name="SC_PA_T_W" />
     <KeyWord name="R" />
     <KeyWord name="AA_ACCLIMA" />
     <KeyWord name="AA_ATOL" />
     <KeyWord name="AA_EG_ACTIVE" />
     <KeyWord name="AA_EG_AX" />
     <KeyWord name="AA_EG_DENOM" />
     <KeyWord name="AA_EG_NUMERA" />
     <KeyWord name="AA_EG_NUM_LA" />
     <KeyWord name="AA_EG_SYN" />
     <KeyWord name="AA_EG_SYNFA" />
     <KeyWord name="AA_EG_TYPE" />
     <KeyWord name="AA_FGREF" />
     <KeyWord name="AA_FGROUP" />
     <KeyWord name="AA_JERKLIMA" />
     <KeyWord name="AA_MEAS_P1_VALID" />
     <KeyWord name="AA_MEAS_P2_VALID" />
     <KeyWord name="AA_MEAS_P3_VALID" />
     <KeyWord name="AA_MEAS_P4_VALID" />
     <KeyWord name="AA_MEAS_POINT1" />
     <KeyWord name="AA_MEAS_POINT2" />
     <KeyWord name="AA_MEAS_POINT3" />
     <KeyWord name="AA_MEAS_POINT4" />
     <KeyWord name="AA_MEAS_SETANGLE" />
     <KeyWord name="AA_MEAS_SETPOINT" />
     <KeyWord name="AA_MEAS_SP_VALID" />
     <KeyWord name="AA_VELOLIMA" />
     <KeyWord name="AC_ACT_FLIM_TYPE" />
     <KeyWord name="AC_ACT_FPERF_LIM" />
     <KeyWord name="AC_ACT_POLE_TOL" />
     <KeyWord name="AC_ACT_TOOL_LENGTH_INDEX" />
     <KeyWord name="P_ACT_TOOL_LENGTH_INDEX" />
     <KeyWord name="AC_ALARM_STAT" />
     <KeyWord name="AC_ASUP" />
     <KeyWord name="AC_AXCTSWA" />
     <KeyWord name="AC_CAEXT_OVR" />
     <KeyWord name="AC_CONE_ANGLE" />
     <KeyWord name="AC_CTOL" />
     <KeyWord name="AC_CTOL_G0_ABS" />
     <KeyWord name="AC_DELT" />
     <KeyWord name="AC_DTBB" />
     <KeyWord name="AC_DTBW" />
     <KeyWord name="AC_DTEB" />
     <KeyWord name="AC_DTEW" />
     <KeyWord name="AC_ESR_TRIGGER" />
     <KeyWord name="AC_FCT0" />
     <KeyWord name="AC_FCT1" />
     <KeyWord name="AC_FCT2" />
     <KeyWord name="AC_FCT3" />
     <KeyWord name="AC_FCTLL" />
     <KeyWord name="AC_FCTUL" />
     <KeyWord name="AC_F_G0" />
     <KeyWord name="AC_FGROUP_MASK" />
     <KeyWord name="AC_FZ" />
     <KeyWord name="AC_IPO_STATE" />
     <KeyWord name="AC_IS_ADD_CHAN" />
     <KeyWord name="AC_IW_STAT" />
     <KeyWord name="AC_IW_TU" />
     <KeyWord name="AC_JOG_CIRCLE_SELECTED" />
     <KeyWord name="AC_JOG_COORD" />
     <KeyWord name="AC_LIFTFAST" />
     <KeyWord name="AC_MEA" />
     <KeyWord name="AC_MEAS_ACT_PLANE" />
     <KeyWord name="AC_MEAS_CHBFR" />
     <KeyWord name="AC_MEAS_CHSFR" />
     <KeyWord name="AC_MEAS_CORNER_ANGLE" />
     <KeyWord name="AC_MEAS_CORNER_SETANGLE" />
     <KeyWord name="AC_MEAS_DIAMETER" />
     <KeyWord name="AC_MEAS_DIR_APPROACH" />
     <KeyWord name="AC_MEAS_D_NUMBER" />
     <KeyWord name="AC_MEAS_FINE_TRANS" />
     <KeyWord name="AC_MEAS_FRAME_SELECT" />
     <KeyWord name="AC_MEAS_INPUT" />
     <KeyWord name="AC_MEAS_LATCH" />
     <KeyWord name="AC_MEAS_NCBFR" />
     <KeyWord name="AC_MEAS_ORIWKS" />
     <KeyWord name="AC_MEAS_P1_COORD" />
     <KeyWord name="AC_MEAS_P2_COORD" />
     <KeyWord name="AC_MEAS_P3_COORD" />
     <KeyWord name="AC_MEAS_P4_COORD" />
     <KeyWord name="AC_MEAS_PFRAME" />
     <KeyWord name="AC_MEAS_RESULTS" />
     <KeyWord name="AC_MEAS_SCALEUNIT" />
     <KeyWord name="AC_MEAS_SEMA" />
     <KeyWord name="AC_MEAS_SET_COORD" />
     <KeyWord name="AC_MEAS_T_NUMBER" />
     <KeyWord name="AC_MEAS_TOOL_LENGTH" />
     <KeyWord name="AC_MEAS_TOOL_MASK" />
     <KeyWord name="AC_MEAS_TYPE" />
     <KeyWord name="AC_MEAS_UIFR" />
     <KeyWord name="AC_MEAS_VALID" />
     <KeyWord name="AC_MEAS_WP_ANGLE" />
     <KeyWord name="AC_MEAS_WP_SETANGLE" />
     <KeyWord name="AC_MONMIN" />
     <KeyWord name="AC_MSNUM" />
     <KeyWord name="AC_MTHNUM" />
     <KeyWord name="AC_M_TOOL_LENGTH_INDEX" />
     <KeyWord name="P_M_TOOL_LENGTH_INDEX" />
     <KeyWord name="AC_OTOL" />
     <KeyWord name="AC_OTOL_G0_ABS" />
     <KeyWord name="AC_OVR" />
     <KeyWord name="AC_PATHACC" />
     <KeyWord name="AC_PATHJERK" />
     <KeyWord name="AC_PATHN" />
     <KeyWord name="AC_PLC_OVR" />
     <KeyWord name="AC_PLTBB" />
     <KeyWord name="AC_PLTEB" />
     <KeyWord name="AC_PREP_ACT_LOAD" />
     <KeyWord name="AC_PREP_ACT_LOAD_GROSS" />
     <KeyWord name="AC_PREP_MAX_LOAD" />
     <KeyWord name="AC_PREP_MAX_LOAD_GROSS" />
     <KeyWord name="AC_PREP_MIN_LOAD" />
     <KeyWord name="AC_PREP_MIN_LOAD_GROSS" />
     <KeyWord name="AC_PROG" />
     <KeyWord name="AC_STAT" />
     <KeyWord name="AC_STOLF" />
     <KeyWord name="AC_SYNA_MEM" />
     <KeyWord name="AC_SYNA_STATE" />
     <KeyWord name="AC_SYNC_ACT_LOAD" />
     <KeyWord name="AC_SYNC_AVERAGE_LOAD" />
     <KeyWord name="AC_SYNC_MAX_LOAD" />
     <KeyWord name="AC_TANEB" />
     <KeyWord name="AC_TC" />
     <KeyWord name="AC_TC_ACKT" />
     <KeyWord name="AC_TC_CMDT" />
     <KeyWord name="P_DLNO" />
     <KeyWord name="P_TOOL" />
     <KeyWord name="P_UIFRNUM" />
     <KeyWord name="P_GFRNUM" />
     <KeyWord name="AC_THREAD_PITCH" />
     <KeyWord name="AC_THREAD_PITCH_ACT" />
     <KeyWord name="AC_THREAD_PITCH_INC" />
     <KeyWord name="AC_TIME" />
     <KeyWord name="AC_TIMEC" />
     <KeyWord name="AC_TIMER" />
     <KeyWord name="AC_TC_" />
     <KeyWord name="AC_TOOL_O_ACT" />
     <KeyWord name="AC_TOOL_O_CORR" />
     <KeyWord name="AC_TOOL_O_CORR_ANGLE" />
     <KeyWord name="AC_TOOL_O_CORRD" />
     <KeyWord name="AC_TOOL_O_CORR_DIR" />
     <KeyWord name="AC_TOOL_O_DIFF" />
     <KeyWord name="AC_TOOL_O_END" />
     <KeyWord name="AC_TOOL_R_ACT" />
     <KeyWord name="AC_TOOL_R_CORR" />
     <KeyWord name="AC_TOOL_R_CORR_ANGLE" />
     <KeyWord name="AC_TOOL_R_CORRD" />
     <KeyWord name="AC_TOOL_R_CORR_DIR" />
     <KeyWord name="AC_TOOL_R_DIFF" />
     <KeyWord name="AC_TOOL_R_END" />
     <KeyWord name="AC_TOTAL_OVR" />
     <KeyWord name="AC_ACTUAL_PARTS" />
     <KeyWord name="AC_ACT_PROG_NET_TIME" />
     <KeyWord name="AC_TRAFO" />
     <KeyWord name="AC_TRAFO_CHAIN" />
     <KeyWord name="AC_TRAFO_CORR_ELEM_P" />
     <KeyWord name="AC_TRAFO_CORR_ELEM_T" />
     <KeyWord name="AC_TRAFO_NAME" />
     <KeyWord name="AC_TRAFO_ORIAX_DIR_P" />
     <KeyWord name="AC_TRAFO_ORIAX_DIR_T" />
     <KeyWord name="AC_TRAFO_ORIAX_LOC" />
     <KeyWord name="AC_TRAFO_PAR" />
     <KeyWord name="AC_TRAFO_PARSET" />
     <KeyWord name="AC_TRAFO_SECTION_P" />
     <KeyWord name="AC_TRAFO_SECTION_T" />
     <KeyWord name="P_TOOLNO" />
     <KeyWord name="P_....._BEFORE_SEARCH_RUN" />
     <KeyWord name="P_TOOLL" />
     <KeyWord name="AC_T_TOOL_LENGTH_INDEX" />
     <KeyWord name="P_T_TOOL_LENGTH_INDEX" />
     <KeyWord name="P_TOOLR" />
     <KeyWord name="AC_WORKAREA_CS_COORD_SYSTEM" />
     <KeyWord name="AC_WORKAREA_CS_LIMIT_MINUS" />
     <KeyWord name="AC_WORKAREA_CS_LIMIT_PLUS" />
     <KeyWord name="AC_WORKAREA_CS_MINUS_ENABLE" />
     <KeyWord name="AC_WORKAREA_CS_PLUS_ENABLE" />
     <KeyWord name="AC_WORKAREA_CS_GROUP" />
     <KeyWord name="AC_VACTB" />
     <KeyWord name="AC_VACTBF" />
     <KeyWord name="AC_VACTW" />
     <KeyWord name="AC_VACTWF" />
     <KeyWord name="AC_VC" />
     <KeyWord name="A_GG" />
     <KeyWord name="A_LINK_TRANS_RATE" />
     <KeyWord name="A_MONIFACT" />
     <KeyWord name="AC_TC_ACKC" />
     <KeyWord name="AC_TC_CMDC" />
     <KeyWord name="AC_TC_DISTANCE" />
     <KeyWord name="AC_TC_FCT" />
     <KeyWord name="AC_TC_LFN" />
     <KeyWord name="AC_TC_LFO" />
     <KeyWord name="AC_TC_LMYN" />
     <KeyWord name="AC_TC_LTN" />
     <KeyWord name="AC_TC_LTO" />
     <KeyWord name="AC_TC_MFN" />
     <KeyWord name="AC_TC_MFO" />
     <KeyWord name="AC_TC_MMYN" />
     <KeyWord name="AC_TC_MTN" />
     <KeyWord name="AC_TC_MTO" />
     <KeyWord name="AC_TC_MTLTN" />
     <KeyWord name="AC_TC_MTTN" />
     <KeyWord name="AC_TC_MTNLOC" />
     <KeyWord name="AC_TC_STATUS" />
     <KeyWord name="AC_TC_THNO" />
     <KeyWord name="AC_TC_TNO" />
     <KeyWord name="AC_TC_TOOLIS" />
     <KeyWord name="P_CHBFRMASK" />
     <KeyWord name="AC_BLOCK_PROGSTATE" />
     <KeyWord name="AC_BLOCKTYPE" />
     <KeyWord name="AC_BLOCKTYPEINFO" />
     <KeyWord name="C_IN" />
     <KeyWord name="AC_F" />
     <KeyWord name="P_TRAFO_PAR" />
     <KeyWord name="P_TRAFO_PARSET" />
     <KeyWord name="P_TRAFO" />
     <KeyWord name="C_OUT" />
     <KeyWord name="AC_G0MODE" />
     <KeyWord name="PC_GCC_STATE" />
     <KeyWord name="P_INCOAP_B" />
     <KeyWord name="P_INCOAP_C" />
     <KeyWord name="P_INCOAP_I" />
     <KeyWord name="P_INCOAP_R" />
     <KeyWord name="P_INCOAP_S16" />
     <KeyWord name="P_INCOAP_S160" />
     <KeyWord name="P_INCOAP_S32" />
     <KeyWord name="P_INCOAP_SIZE" />
     <KeyWord name="P_ISO2_HNO" />
     <KeyWord name="P_MAGNS" />
     <KeyWord name="MM_PROTOC_NUM_ETP_OEM_TYP" />
     <KeyWord name="AC_OLD_PROG_NET_TIME" />
     <KeyWord name="AC_OLD_PROG_NET_TIME_COUNT" />
     <KeyWord name="PA_ACCLIMA" />
     <KeyWord name="PA_JERKLIMA" />
     <KeyWord name="PA_VELOLIMA" />
     <KeyWord name="PC_TCARR_AX_OFFSET" />
     <KeyWord name="PC_TCARR_AX_VECT" />
     <KeyWord name="PC_TCARR_OFFSET" />
     <KeyWord name="PC_TRAFO_NUM" />
     <KeyWord name="PC_TRAFO_ROT_CHAIN_INDEX" />
     <KeyWord name="PC_TRAFO_ROT_CHAN_AX_EX" />
     <KeyWord name="PC_TRAFO_ROT_CHAN_AX_IN" />
     <KeyWord name="AC_CUT_INV" />
     <KeyWord name="AC_CUTMOD" />
     <KeyWord name="AC_CUTMODK" />
     <KeyWord name="AC_CUTMODKA" />
     <KeyWord name="P_CUTMODKA" />
     <KeyWord name="P_EG_BC" />
     <KeyWord name="P_MTHSDC" />
     <KeyWord name="P_OFFN" />
     <KeyWord name="P_ORI_DIFF" />
     <KeyWord name="P_ORI_POS" />
     <KeyWord name="P_ORI_SOL" />
     <KeyWord name="P_ORI_STAT" />
     <KeyWord name="AC_PROG_NET_TIME_TRIGGER" />
     <KeyWord name="MM_PROTOC_USER_ACTIVE" />
     <KeyWord name="P_TC" />
     <KeyWord name="P_TCANG" />
     <KeyWord name="P_TCDIFF" />
     <KeyWord name="P_TCNUM" />
     <KeyWord name="P_TCSOL" />
     <KeyWord name="P_TCSTAT" />
     <KeyWord name="P_AD" />
     <KeyWord name="P_TOOL_O" />
     <KeyWord name="P_TOOL_O_R" />
     <KeyWord name="AC_REQUIRED_PARTS" />
     <KeyWord name="AC_ROT_SYS" />
     <KeyWord name="AC_SPECIAL_PARTS" />
     <KeyWord name="AC_SPLITBLOCK" />
     <KeyWord name="AC_TIMES" />
     <KeyWord name="AC_TIMESC" />
     <KeyWord name="AC_TOFFCR" />
     <KeyWord name="AC_TOFFL" />
     <KeyWord name="AC_TOFF" />
     <KeyWord name="AC_TOFFR" />
     <KeyWord name="P_TH_OF_D" />
     <KeyWord name="AC_TOTAL_PARTS" />
     <KeyWord name="AC_TRANS_SYS" />
     <KeyWord name="VA_CC_COMP_VAL" />
     <KeyWord name="VA_EG_SYNCDIFF" />
     <KeyWord name="VA_EG_SYNCDIFF_S" />
     <KeyWord name="VA_SYNCDIFF" />
     <KeyWord name="VC_TOOL_O" />
     <KeyWord name="VC_TOOL_O_DIFF" />
     <KeyWord name="VC_TOOLO_STAT" />
     <KeyWord name="VC_TOOL_R" />
     <KeyWord name="VC_TOOL_R_DIFF" />
     <KeyWord name="VC_TOOLR_STAT" />
     <KeyWord name="SC_MDD_DRY_RUN_FEED" />
     <KeyWord name="SC_MDD_THREAD_START_ANGLE" />
     <KeyWord name="AA_ACS_REL" />
     <KeyWord name="AA_DELT" />
     <KeyWord name="AA_DIAM_STAT" />
     <KeyWord name="AA_DTBW" />
     <KeyWord name="AA_DTEPW" />
     <KeyWord name="AA_DTEW" />
     <KeyWord name="AA_DTSB" />
     <KeyWord name="AA_DTSW" />
     <KeyWord name="AA_IBC" />
     <KeyWord name="AA_IB_CORR" />
     <KeyWord name="AA_ITR" />
     <KeyWord name="AA_IW_CORR" />
     <KeyWord name="AA_MW" />
     <KeyWord name="AA_MW1" />
     <KeyWord name="AA_MW2" />
     <KeyWord name="AA_MW3" />
     <KeyWord name="AA_MW4" />
     <KeyWord name="AA_PCS_REL" />
     <KeyWord name="AA_SCC_STAT" />
     <KeyWord name="AA_TOFF" />
     <KeyWord name="AA_TOFF_LIMIT" />
     <KeyWord name="AA_TOFF_PREP_DIFF" />
     <KeyWord name="AA_TOFF_VAL" />
     <KeyWord name="AA_VACTW" />
     <KeyWord name="AC_RETPOINT" />
     <KeyWord name="AA_IBN" />
     <KeyWord name="AA_IEN" />
     <KeyWord name="AC_DRF" />
     <KeyWord name="AA_MOTEND" />
     <KeyWord name="VA_IB" />
     <KeyWord name="VA_IBC" />
     <KeyWord name="VA_ITR" />
     <KeyWord name="VA_IW" />
     <KeyWord name="AA_ACC" />
     <KeyWord name="AA_ACC_PERCENT" />
     <KeyWord name="AA_ACT_INDEX_AX_POS_NO" />
     <KeyWord name="AA_ALARM_STAT" />
     <KeyWord name="AA_AXCHANGE_STAT" />
     <KeyWord name="AA_AXCHANGE_TYP" />
     <KeyWord name="AA_AX_DISABLE" />
     <KeyWord name="AA_AX_DISABLE_SRC" />
     <KeyWord name="AA_BCS_OFFSET" />
     <KeyWord name="AA_BRAKE_CONDB" />
     <KeyWord name="AA_BRAKE_CONDM" />
     <KeyWord name="AA_BRAKE_STATE" />
     <KeyWord name="AA_CHANNO" />
     <KeyWord name="AA_COLLPOS" />
     <KeyWord name="AA_COUP_ACT" />
     <KeyWord name="AA_COUP_CORR" />
     <KeyWord name="AA_COUP_CORR_DIST" />
     <KeyWord name="AA_DEPAXO" />
     <KeyWord name="AA_DTBB" />
     <KeyWord name="AA_DTBREB" />
     <KeyWord name="AA_DTBREB_CMD" />
     <KeyWord name="AA_DTBREB_CORR" />
     <KeyWord name="AA_DTBREB_DEP" />
     <KeyWord name="AA_DTBREM" />
     <KeyWord name="AA_DTBREM_CMD" />
     <KeyWord name="AA_DTBREM_CORR" />
     <KeyWord name="AA_DTBREM_DEP" />
     <KeyWord name="AA_DTEB" />
     <KeyWord name="AA_DTEPB" />
     <KeyWord name="AA_ENC1_ACTIVE" />
     <KeyWord name="AA_ENC2_ACTIVE" />
	 <KeyWord name="AA_ENC_ACTIVE" />
     <KeyWord name="AA_ESR_ENABLE" />
     <KeyWord name="AA_ESR_STAT" />
     <KeyWord name="AA_ESR_TRIGGER" />
     <KeyWord name="AA_FIX_POINT_SELECTED" />
     <KeyWord name="AA_IBN_CORR" />
     <KeyWord name="AA_IEN_CORR" />
     <KeyWord name="AA_INPOS_STAT" />
     <KeyWord name="AA_IN_SYNC" />
     <KeyWord name="AA_IPO_NC_CHANAX" />
     <KeyWord name="AA_JERK_COUNT" />
     <KeyWord name="AA_JERK_TIME" />
     <KeyWord name="AA_JERK_TOT" />
     <KeyWord name="AA_JOG_POS_ACT" />
     <KeyWord name="AA_JOG_POS_SELECTED" />
     <KeyWord name="AA_LEAD_P" />
     <KeyWord name="AA_LEAD_P_TURN" />
     <KeyWord name="AA_LEAD_SP" />
     <KeyWord name="AA_LEAD_SV" />
     <KeyWord name="AA_LEAD_V" />
     <KeyWord name="AA_LOAD_SMOOTH" />
     <KeyWord name="AA_MACHAX" />
     <KeyWord name="AA_MASL_DEF" />
     <KeyWord name="AA_MASL_STAT" />
     <KeyWord name="AA_MEAACT" />
     <KeyWord name="AA_MM" />
     <KeyWord name="AA_MM1" />
     <KeyWord name="AA_MM2" />
     <KeyWord name="AA_MM3" />
     <KeyWord name="AA_MM4" />
     <KeyWord name="AA_OFF" />
     <KeyWord name="AA_OFF_LIMIT" />
     <KeyWord name="AA_OFF_VAL" />
     <KeyWord name="AA_FIX_ON_POINT" />
     <KeyWord name="AA_OSCILL_BREAK_POS1" />
     <KeyWord name="AA_OSCILL_BREAK_POS2" />
     <KeyWord name="AA_OSCILL_REVERSE_POS1" />
     <KeyWord name="AA_OSCILL_REVERSE_POS2" />
     <KeyWord name="AA_OVR" />
     <KeyWord name="AA_PLC_OVR" />
     <KeyWord name="AA_POLFA" />
     <KeyWord name="AA_POLFA_VALID" />
     <KeyWord name="AA_POSRES" />
     <KeyWord name="AA_POWER_SMOOTH" />
     <KeyWord name="AA_PROG_INDEX_AX_POS_NO" />
     <KeyWord name="AA_REF" />
     <KeyWord name="AA_REPOS_DELAY" />
     <KeyWord name="AA_SCPAR" />
     <KeyWord name="AA_SNGLAX_STAT" />
     <KeyWord name="AA_SOFTENDN" />
     <KeyWord name="AA_SOFTENDP" />
     <KeyWord name="AA_STAT" />
     <KeyWord name="AA_SYNC" />
     <KeyWord name="AA_SYNCDIFF" />
     <KeyWord name="AA_SYNCDIFF_STAT" />
     <KeyWord name="AA_TOTAL_OVR" />
     <KeyWord name="AA_TRAVEL_COUNT" />
     <KeyWord name="AA_TRAVEL_COUNT_HS" />
     <KeyWord name="AA_TRAVEL_DIST" />
     <KeyWord name="AA_TRAVEL_DIST_HS" />
     <KeyWord name="AA_TRAVEL_TIME" />
     <KeyWord name="AA_TRAVEL_TIME_HS" />
     <KeyWord name="AA_TYP" />
     <KeyWord name="AA_TYPE" />
     <KeyWord name="AA_VACTB" />
     <KeyWord name="AA_VACTM" />
     <KeyWord name="AA_VC" />
     <KeyWord name="AC_RPVALID" />
     <KeyWord name="VA_COUP_OFFS" />
     <KeyWord name="AA_COUP_OFFS" />
     <KeyWord name="MC_DISPLAY_AXIS" />
     <KeyWord name="AA_FOC" />
     <KeyWord name="VA_FXS_INFO" />
     <KeyWord name="AA_FXS" />
     <KeyWord name="AC_PRESET" />
     <KeyWord name="VA_TRACK_ERR_CONTR" />
     <KeyWord name="VA_ABSOLUTE_ENC_DELTA_INIT" />
     <KeyWord name="VA_ABSOLUTE_ENC_ERR_CNT" />
     <KeyWord name="VA_ABSOLUTE_ENC_STATE" />
     <KeyWord name="VA_ABSOLUTE_ENC_ZERO_MON_MAX" />
     <KeyWord name="VA_AX_FORCE" />
     <KeyWord name="VA_CC_COMP_VAL_TOTAL" />
     <KeyWord name="VA_CEC_COMP_VAL" />
     <KeyWord name="VA_CPSYNC2" />
     <KeyWord name="VA_CURR" />
     <KeyWord name="VA_DESVAL_FILTERS_ACTIVE" />
     <KeyWord name="VA_DESVAL_FILTERS_DELAY_1" />
     <KeyWord name="VA_DESVAL_FILTERS_DELAY_2" />
     <KeyWord name="VA_DESVAL_FILTERS_DELTA_POS" />
     <KeyWord name="VA_DIST_TORQUE" />
     <KeyWord name="VA_DPE" />
     <KeyWord name="VA_ENC1_COMP_VAL" />
     <KeyWord name="VA_ENC2_COMP_VAL" />
     <KeyWord name="VA_ENC_ZERO_MON_ACCESS_CNT" />
     <KeyWord name="VA_ENC_ZERO_MON_ACT" />
     <KeyWord name="VA_ENC_ZERO_MON_ERR_CNT" />
     <KeyWord name="VA_ENC_ZERO_MON_INIT" />
     <KeyWord name="VA_FOC" />
     <KeyWord name="VA_FXS" />
     <KeyWord name="VA_IM" />
     <KeyWord name="VA_IM1" />
     <KeyWord name="VA_IM2" />
     <KeyWord name="VA_IPO_NC_CHANAX" />
     <KeyWord name="VA_LAG_ERROR" />
     <KeyWord name="VA_LOAD" />
     <KeyWord name="VA_MEC_COMP_VAL" />
     <KeyWord name="VA_MOT_CLAMPING_STATE" />
     <KeyWord name="VA_MOT_SENSOR_ANA" />
     <KeyWord name="VA_MOT_SENSOR_CONF" />
     <KeyWord name="VA_MOT_SENSOR_DIGI" />
     <KeyWord name="VA_POSCTRL_MODE" />
     <KeyWord name="VA_POWER" />
     <KeyWord name="VA_SCE" />
     <KeyWord name="VA_STOPSI" />
     <KeyWord name="VA_SYNCDIFF_STAT" />
     <KeyWord name="VA_TEMP_COMP_VAL" />
     <KeyWord name="VA_TORQUE" />
     <KeyWord name="VA_TORQUE_AT_LIMIT" />
     <KeyWord name="VA_VACTM" />
     <KeyWord name="AA_IW" />
     <KeyWord name="AA_IM" />
     <KeyWord name="AA_IB" />
     <KeyWord name="AC_CONSTCUT_S" />
     <KeyWord name="AC_SDIR" />
     <KeyWord name="AC_SGEAR" />
     <KeyWord name="AC_SMAXACC" />
     <KeyWord name="AC_SMAXACC_INFO" />
     <KeyWord name="AC_SMAXVELO" />
     <KeyWord name="AC_SMAXVELO_INFO" />
     <KeyWord name="AC_SMINVELO" />
     <KeyWord name="AC_SMINVELO_INFO" />
     <KeyWord name="AC_SMODE" />
     <KeyWord name="AC_SPIND_STATE" />
     <KeyWord name="AC_S_TYPE" />
     <KeyWord name="AC_SVC" />
     <KeyWord name="AA_S" />
     <KeyWord name="P_S" />
     <KeyWord name="GWPS}" />
     <KeyWord name="P_SMODE" />
     <KeyWord name="VC_SGEAR" />
     <KeyWord name="AC_FIFOx" />
     <KeyWord name="AC_MARKER" />
     <KeyWord name="AC_PARAM" />
     <KeyWord name="P_WORKAREA_CS_COORD_SYSTEM" />
     <KeyWord name="P_WORKAREA_CS_LIMIT_MINUS" />
     <KeyWord name="P_WORKAREA_CS_LIMIT_PLUS" />
     <KeyWord name="P_WORKAREA_CS_MINUS_ENABLE" />
     <KeyWord name="P_WORKAREA_CS_PLUS_ENABLE" />
     <KeyWord name="MC_TOOL_MANAGEMENT_MASK" />
     <KeyWord name="MC_MM_NUM_BASE_FRAMES" />
     <KeyWord name="MC_MM_SYSTEM_FRAME_MASK" />
     <KeyWord name="MC_MM_TOOL_DATA_CHG_BUFF_SIZE" />
     <KeyWord name="AN_POWERON_TIME" />
     <KeyWord name="AN_SETUP_TIME" />
     <KeyWord name="AN_PERSDIAG" />
     <KeyWord name="P_NCBFR" />
     <KeyWord name="NK_AXIS" />
     <KeyWord name="NK_A_OFF" />
     <KeyWord name="NK_NAME" />
     <KeyWord name="NK_NEXT" />
     <KeyWord name="NK_OFF_DIR" />
     <KeyWord name="NK_PARALLEL" />
     <KeyWord name="NK_SWITCH_INDEX" />
     <KeyWord name="NK_SWITCH_POS" />
     <KeyWord name="NK_TYPE" />
     <KeyWord name="NK_SWITCH" />
     <KeyWord name="SN_PA_CENT_ABS" />
     <KeyWord name="SN_PA_CENT_ORD" />
     <KeyWord name="SN_PA_CONT_ABS" />
     <KeyWord name="SN_PA_CONT_ORD" />
     <KeyWord name="SN_PA_MINUS_LIM" />
     <KeyWord name="SN_PA_PLUS_LIM" />
     <KeyWord name="SN_PA_ACTIV_IMMED" />
     <KeyWord name="SN_PA_CONT_NUM" />
     <KeyWord name="SN_PA_CONT_TYP" />
     <KeyWord name="SN_PA_LIM_3DIM" />
     <KeyWord name="SN_PA_ORI" />
     <KeyWord name="SN_PA_T_W" />
     <KeyWord name="NP_1ST_PROT" />
     <KeyWord name="NP_INDEX" />
     <KeyWord name="NP_BIT_NO" />
     <KeyWord name="NP_CHAIN_ELEM" />
     <KeyWord name="NP_COLL_PAIR" />
     <KeyWord name="NP_SAFETY_DIST" />
     <KeyWord name="NP_ADD" />
     <KeyWord name="NP_ANG" />
     <KeyWord name="NP_COLOR" />
     <KeyWord name="NP_DIR" />
     <KeyWord name="NP_D_LEVEL" />
     <KeyWord name="NP_FILENAME" />
     <KeyWord name="NP_NAME" />
     <KeyWord name="NP_NEXT" />
     <KeyWord name="NP_NEXTP" />
     <KeyWord name="NP_OFF" />
     <KeyWord name="NP_PARA" />
     <KeyWord name="NP_TYPE" />
     <KeyWord name="NP_USAGE" />
     <KeyWord name="NP_INIT_STAT" />
     <KeyWord name="NP_PROT_COLOR" />
     <KeyWord name="NP_PROT_D_LEVEL" />
     <KeyWord name="NP_PROT_NAME" />
     <KeyWord name="NP_PROT_TYPE" />
     <KeyWord name="NP_T_ANG" />
     <KeyWord name="NP_T_DIR" />
     <KeyWord name="NP_T_FILENAME" />
     <KeyWord name="NP_T_NAME" />
     <KeyWord name="NP_T_OFF" />
     <KeyWord name="NP_T_PARA" />
     <KeyWord name="NP_T_TYPE" />
     <KeyWord name="NT_AUX_POS" />
     <KeyWord name="NT_BASE_ORIENT" />
     <KeyWord name="NT_BASE_ORIENT_NORMAL" />
     <KeyWord name="NT_BASE_TOOL" />
     <KeyWord name="NT_BASE_TOOL_COMP" />
     <KeyWord name="NT_CLOSE_CHAIN_P" />
     <KeyWord name="NT_CLOSE_CHAIN_T" />
     <KeyWord name="NT_CNTRL" />
     <KeyWord name="NT_CORR_ELEM_P" />
     <KeyWord name="NT_CORR_ELEM_T" />
     <KeyWord name="NT_GEO_AX_NAME" />
     <KeyWord name="NT_HIRTH_INC" />
     <KeyWord name="NT_HIRTH_OFF" />
     <KeyWord name="NT_IDENT" />
     <KeyWord name="NT_IGNORE_TOOL_ORIENT" />
     <KeyWord name="NT_NAME" />
     <KeyWord name="NT_OA_TRAFO_TYPE" />
     <KeyWord name="NT_P_CHAIN_FIRST_ELEM" />
     <KeyWord name="NT_P_CHAIN_LAST_ELEM" />
     <KeyWord name="NT_POLE_LIMIT" />
     <KeyWord name="NT_POLE_SIDE_FIX" />
     <KeyWord name="NT_POLE_TOL" />
     <KeyWord name="NT_POLE_TOL_FACTOR" />
     <KeyWord name="NT_ROT_AX_CNT" />
     <KeyWord name="NT_ROT_AX_MAX" />
     <KeyWord name="NT_ROT_AX_MIN" />
     <KeyWord name="NT_ROT_AX_NAME" />
     <KeyWord name="NT_ROT_AX_OFFSET" />
     <KeyWord name="NT_ROT_AX_POS" />
     <KeyWord name="NT_ROT_OFFSET_FROM_FRAME" />
     <KeyWord name="NT_T_CHAIN_FIRST_ELEM" />
     <KeyWord name="NT_T_CHAIN_LAST_ELEM" />
     <KeyWord name="NT_TRAFO_INCLUDES_TOOL" />
     <KeyWord name="NT_TRAFO_INDEX" />
     <KeyWord name="NT_TRAFO_TYPE" />
     <KeyWord name="NT_T_REF_ELEM" />
     <KeyWord name="RG" />
     <KeyWord name="A_DBB" />
     <KeyWord name="A_DBD" />
     <KeyWord name="A_DBR" />
	 <KeyWord name="A_DBSB" />
     <KeyWord name="A_DBSW" />
     <KeyWord name="A_DBW" />
     <KeyWord name="A_DLB" />
     <KeyWord name="A_DLD" />
     <KeyWord name="A_DLR" />
     <KeyWord name="A_DLW" />
     <KeyWord name="A_DPB_IN" />
     <KeyWord name="A_DPB_OUT" />
     <KeyWord name="A_DP_IN_CONF" />
     <KeyWord name="A_DP_IN_LENGTH" />
     <KeyWord name="A_DP_IN_STATE" />
     <KeyWord name="A_DP_IN_VALID" />
     <KeyWord name="A_DP_OUT_CONF" />
     <KeyWord name="A_DP_OUT_LENGTH" />
     <KeyWord name="A_DP_OUT_STATE" />
     <KeyWord name="A_DP_OUT_VALID" />
     <KeyWord name="A_DPR_IN" />
     <KeyWord name="A_DPR_OUT" />
     <KeyWord name="A_DPSB_IN" />
     <KeyWord name="A_DPSB_OUT" />
     <KeyWord name="A_DPSD_IN" />
     <KeyWord name="A_DPSD_OUT" />
     <KeyWord name="A_DPSW_IN" />
     <KeyWord name="A_DPSW_OUT" />
     <KeyWord name="A_DPW_IN" />
     <KeyWord name="A_DPW_OUT" />
     <KeyWord name="A_INCO" />
     <KeyWord name="AN_ACTIVATE_COLL_CHECK" />
     <KeyWord name="A_INA" />
     <KeyWord name="A_OUTA" />
     <KeyWord name="AN_AUXFU_LIST_CHANNO" />
     <KeyWord name="AN_AUXFU_LIST_ENDINDEX" />
     <KeyWord name="AN_AUXFU_LIST_GROUPINDEX" />
     <KeyWord name="AN_AXCTAS" />
     <KeyWord name="AN_AXCTSWA" />
     <KeyWord name="AN_AXCTSWE" />
     <KeyWord name="AN_ESR_TRIGGER" />
     <KeyWord name="AN_CEC_DIRECTION" />
     <KeyWord name="AN_CEC_INPUT_AXIS" />
     <KeyWord name="AN_CEC_INPUT_NCU" />
     <KeyWord name="AN_CEC_IS_MODULO" />
     <KeyWord name="AN_CEC_MAX" />
     <KeyWord name="AN_CEC_MIN" />
     <KeyWord name="AN_CEC_MULT_BY_TABLE" />
     <KeyWord name="AN_CEC_OUTPUT_AXIS" />
     <KeyWord name="AN_CEC_OUTPUT_NCU" />
     <KeyWord name="AN_CEC_STEP" />
     <KeyWord name="AN_CEC_TYPE" />
     <KeyWord name="AN_COLL_CHECK_OFF" />
     <KeyWord name="AN_COLLEXT_LOAD" />
     <KeyWord name="AN_COLL_IPO_ACTIVE" />
     <KeyWord name="AN_COLL_IPO_LIMIT" />
     <KeyWord name="AN_COLL_LOAD" />
     <KeyWord name="AN_COLL_MEM_AVAILABLE" />
     <KeyWord name="AN_COLL_MEM_USE_ACT" />
     <KeyWord name="AN_COLL_MEM_USE_MAX" />
     <KeyWord name="AN_COLL_MEM_USE_MIN" />
     <KeyWord name="AN_COLL_PAIRS_ACT" />
     <KeyWord name="AN_COLL_PAIRS_DEF" />
     <KeyWord name="AN_COLL_STATE" />
     <KeyWord name="AN_COLL_STATE_COND" />
     <KeyWord name="AN_COLL_TIMEOUT_CNTR" />
     <KeyWord name="AN_CUTRACE" />
     <KeyWord name="AN_FACETS_ACT" />
     <KeyWord name="AN_FACETS_AVAILABLE" />
     <KeyWord name="AN_FACETS_INTERN_ACT" />
     <KeyWord name="AN_FACETS_INTERN_AVAILABLE" />
     <KeyWord name="AN_FACETS_INTERN_MAX" />
     <KeyWord name="AN_FACETS_INTER_MIN" />
     <KeyWord name="AN_FACETS_MAX" />
     <KeyWord name="AN_FACETS_MIN" />
     <KeyWord name="AN_IPO_ACT_LOAD" />
     <KeyWord name="AN_IPO_CHANAX" />
     <KeyWord name="AN_IPO_LOAD_LIMIT" />
     <KeyWord name="AN_IPO_LOAD_PERCENT" />
     <KeyWord name="AN_IPO_MAX_LOAD" />
     <KeyWord name="AN_IPO_MIN_LOAD" />
     <KeyWord name="AN_KIN_CHAIN_ELEM_ACT" />
     <KeyWord name="AN_LAI_AX_IS_AXCTAX" />
     <KeyWord name="AN_LAI_AX_IS_LEADLINKAX" />
     <KeyWord name="AN_LAI_AX_IS_LINKAX" />
     <KeyWord name="AN_LAI_AX_TO_IPO_NC_CHANAX" />
     <KeyWord name="AN_LAI_AX_TO_MACHAX" />
     <KeyWord name="AN_LINK_COMM_STATE" />
     <KeyWord name="AN_LINK_CONN_RCV" />
     <KeyWord name="AN_LINK_CONN_SIZE_LINKVAR" />
     <KeyWord name="AN_LINK_CONN_SND" />
     <KeyWord name="AN_LINK_TRANS_RATE_LAST" />
     <KeyWord name="AN_LINK_TRANS_RATE_LAST_SUM" />
     <KeyWord name="AN_MEC_INPUT_AXIS" />
     <KeyWord name="AN_MEC_INPUT_POS" />
     <KeyWord name="AN_MEC_NUM_POINTS" />
     <KeyWord name="AN_MEC_OUTPUT_AXIS" />
     <KeyWord name="AN_MEC_SCALING_METRIC" />
     <KeyWord name="AN_MEC_VAL" />
     <KeyWord name="AN_POWERON_STATE" />
     <KeyWord name="AN_PREP_ACT_LOAD" />
     <KeyWord name="AN_PREP_ACT_LOAD_GROSS" />
     <KeyWord name="AN_PREP_MAX_LOAD" />
     <KeyWord name="AN_PREP_MAX_LOAD_GROSS" />
     <KeyWord name="AN_PREP_MIN_LOAD" />
     <KeyWord name="AN_PREP_MIN_LOAD_GROSS" />
     <KeyWord name="AN_PROT_AREA_ELEM_ACT" />
     <KeyWord name="AN_PROT_AREA_ELEM_DEF" />
     <KeyWord name="AN_PROT_AREA_PRIM_ACT" />
     <KeyWord name="AN_PROT_AREA_PRIM_DEF" />
     <KeyWord name="AN_PROT_AREAS_ACT" />
     <KeyWord name="AN_PROT_AREAS_DEF" />
     <KeyWord name="AN_REBOOT_DELAY_TIME" />
     <KeyWord name="AN_ROBIN" />
     <KeyWord name="AN_ROBOUT" />
     <KeyWord name="AN_SERVO_ACT_LOAD" />
     <KeyWord name="AN_SERVO_MAX_LOAD" />
     <KeyWord name="AN_SERVO_MIN_LOAD" />
     <KeyWord name="AN_SIM_CHAN_MASK" />
     <KeyWord name="AN_SIM_MAX_IPOSTEP" />
     <KeyWord name="AN_SLTRACE" />
     <KeyWord name="AN_SYNC_ACT_LOAD" />
     <KeyWord name="AN_SYNC_MAX_LOAD" />
     <KeyWord name="AN_SYNC_TO_IPO" />
     <KeyWord name="AN_TIMER" />
     <KeyWord name="AN_T_PROT_ELEM_ACT" />
     <KeyWord name="AN_VMODEL_STATUS" />
     <KeyWord name="A_PBB_IN" />
     <KeyWord name="A_PBB_OUT" />
     <KeyWord name="A_PBD_IN" />
     <KeyWord name="A_PBD_OUT" />
     <KeyWord name="A_PBR_IN" />
     <KeyWord name="A_PBR_OUT" />
     <KeyWord name="A_PBW_IN" />
     <KeyWord name="A_PBW_OUT" />
     <KeyWord name="A_PROBE" />
     <KeyWord name="A_PROBE_LIMITED" />
     <KeyWord name="A_STOPESI" />
     <KeyWord name="P_NCBFRMASK" />
     <KeyWord name="A_IN" />
     <KeyWord name="A_OUT" />
     <KeyWord name="MM_PROTOC_NUM_ETPD_STD_LIST" />
     <KeyWord name="MM_PROTOC_NUM_ETPD_OEM_LIST" />
     <KeyWord name="P_MODEL_SCALING_OVL" />
     <KeyWord name="PN_CHANGE_CNTR_NK_DATA" />
     <KeyWord name="PN_CHANGE_CNTR_NK_ELEM" />
     <KeyWord name="PN_CHANGE_CNTR_NK_SWITCH" />
     <KeyWord name="PN_CHANGE_CNTR_NP_DATA" />
     <KeyWord name="PN_CHANGE_CNTR_NT_DATA" />
     <KeyWord name="PN_ROBIN" />
     <KeyWord name="PN_ROBOUT" />
     <KeyWord name="MM_PROTOC_NUM_FILES" />
     <KeyWord name="A_PROTOC" />
     <KeyWord name="A_PROT_LOCK" />
     <KeyWord name="VA_DP_ACT_TEL" />
     <KeyWord name="SN_MDB_JOG_CONT_MODE_LEVELTRIGGRD" />
     <KeyWord name="SN_MDB_JOG_REV_IS_ACTIVE" />
     <KeyWord name="SN_MDD_JOG_REV_SET_VELO" />
     <KeyWord name="SN_MDD_JOG_SET_VELO" />
     <KeyWord name="SN_MDD_JOG_SPIND_SET_VELO" />
     <KeyWord name="SN_MDD_JOG_VAR_INCR_SIZE" />
     <KeyWord name="AN_LANGUAGE_ON_HMI" />
     <KeyWord name="MN_MM_KIND_OF_SUMCORR" />
     <KeyWord name="MN_MAX_CUTTING_EDGE_NO" />
     <KeyWord name="MN_MM_NUM_TOOL_ADAPTER" />
     <KeyWord name="MN_MM_MAX_CUTTING_EDGE_PERTOOL" />
     <KeyWord name="MN_MM_MAX_SUMCORR_PER_CUTTEDGE" />
     <KeyWord name="MN_MM_NUM_SUMCORR" />
     <KeyWord name="MN_MM_TOOL_MANAGEMENT_MASK" />
     <KeyWord name="AN_NCK_VERSION" />
     <KeyWord name="MN_MM_NUM_GLOBAL_BASE_FRAMES" />
     <KeyWord name="MN_MM_NUM_CCS_TOA_PARAM" />
     <KeyWord name="MN_MM_NUM_CCS_MON_PARAM" />
     <KeyWord name="MN_MM_NUM_CC_TOA_PARAM" />
     <KeyWord name="MN_MM_NUM_CC_MON_PARAM" />
     <KeyWord name="MN_MM_NUM_GLOBAL_G_FRAMES" />
     <KeyWord name="MN_MM_NUM_CCS_MAGLOC_PARAM" />
     <KeyWord name="MN_MM_NUM_CC_MAGLOC_PARAM" />
     <KeyWord name="MN_MM_NUM_CCS_MAGAZINE_PARAM" />
     <KeyWord name="MN_MM_NUM_CC_MAGAZINE_PARAM" />
     <KeyWord name="MN_MM_NUM_MAGAZINE_LOCATION" />
     <KeyWord name="MN_MM_NUM_MAGAZINE" />
     <KeyWord name="MN_MM_NUM_CCS_MULTITOOL_PARAM" />
     <KeyWord name="MN_MM_NUM_CC_MULTITOOL_PARAM" />
     <KeyWord name="MN_MM_NUM_CCS_MTLOC_PARAM" />
     <KeyWord name="MN_MM_NUM_CC_MTLOC_PARAM" />
     <KeyWord name="MN_MM_NUM_CCS_TDA_PARAM" />
     <KeyWord name="MN_MM_NUM_CC_TDA_PARAM" />
     <KeyWord name="MN_MM_NUM_GLOBAL_USER_FRAMES" />
     <KeyWord name="TC_ADPT1" />
     <KeyWord name="TC_ADPT2" />
     <KeyWord name="TC_ADPT3" />
     <KeyWord name="TC_ADPT_ANG" />
     <KeyWord name="TC_ADPT_ANG_CONST" />
     <KeyWord name="TC_ADPT_DIR" />
     <KeyWord name="TC_ADPT_OFF" />
     <KeyWord name="TC_ADPTT" />
     <KeyWord name="TC_MTPCSx" />
     <KeyWord name="TC_MTPPCSx" />
     <KeyWord name="TC_MTP2" />
     <KeyWord name="TC_MTP_KD" />
     <KeyWord name="TC_MTPN" />
     <KeyWord name="TC_MTP7" />
     <KeyWord name="TC_MTP_POS" />
     <KeyWord name="TC_MTP_PROTA" />
     <KeyWord name="TC_MTP6" />
     <KeyWord name="TC_MTP3" />
     <KeyWord name="TC_MTP4" />
     <KeyWord name="TC_MTP5" />
     <KeyWord name="TC_MTP8" />
     <KeyWord name="TC_MTPCx" />
     <KeyWord name="TC_MTPPCx" />
     <KeyWord name="P_MTOOLMT" />
     <KeyWord name="P_MTOOLN" />
     <KeyWord name="TC_TPCSx" />
     <KeyWord name="TC_MAPCSx" />
     <KeyWord name="TC_DPCSx" />
     <KeyWord name="TC_MPPCSx" />
     <KeyWord name="TC_MOPCSx" />
     <KeyWord name="TC_TCARR_CORR_ELEM1" />
     <KeyWord name="TC_TCARR_CORR_ELEM2" />
     <KeyWord name="TC_TCARR_CORR_ELEM3" />
     <KeyWord name="TC_TCARR_CORR_ELEM4" />
     <KeyWord name="TC_CARR_KIN_CNTRL" />
     <KeyWord name="TC_CARR_KIN_PART_END" />
     <KeyWord name="TC_CARR_KIN_PART_START" />
     <KeyWord name="TC_CARR_KIN_ROTAX_NAME" />
     <KeyWord name="TC_CARR_KIN_TOOL_END" />
     <KeyWord name="TC_CARR_KIN_TOOL_START" />
     <KeyWord name="TC_CARR1" />
     <KeyWord name="TC_CARR10" />
     <KeyWord name="TC_CARR11" />
     <KeyWord name="TC_CARR12" />
     <KeyWord name="TC_CARR13" />
     <KeyWord name="TC_CARR14" />
     <KeyWord name="TC_CARR15" />
     <KeyWord name="TC_CARR16" />
     <KeyWord name="TC_CARR17" />
     <KeyWord name="TC_CARR18" />
     <KeyWord name="TC_CARR19" />
     <KeyWord name="TC_CARR2" />
     <KeyWord name="TC_CARR20" />
     <KeyWord name="TC_CARR21" />
     <KeyWord name="TC_CARR22" />
     <KeyWord name="TC_CARR23" />
     <KeyWord name="TC_CARR24" />
     <KeyWord name="TC_CARR25" />
     <KeyWord name="TC_CARR26" />
     <KeyWord name="TC_CARR27" />
     <KeyWord name="TC_CARR28" />
     <KeyWord name="TC_CARR29" />
     <KeyWord name="TC_CARR3" />
     <KeyWord name="TC_CARR30" />
     <KeyWord name="TC_CARR31" />
     <KeyWord name="TC_CARR32" />
     <KeyWord name="TC_CARR33" />
     <KeyWord name="TC_CARR34" />
     <KeyWord name="TC_CARR35" />
     <KeyWord name="TC_CARR36" />
     <KeyWord name="TC_CARR37" />
     <KeyWord name="TC_CARR38" />
     <KeyWord name="TC_CARR39" />
     <KeyWord name="TC_CARR4" />
     <KeyWord name="TC_CARR40" />
     <KeyWord name="TC_CARR41" />
     <KeyWord name="TC_CARR42" />
     <KeyWord name="TC_CARR43" />
     <KeyWord name="TC_CARR44" />
     <KeyWord name="TC_CARR45" />
     <KeyWord name="TC_CARR46" />
     <KeyWord name="TC_CARR5" />
     <KeyWord name="TC_CARR55" />
     <KeyWord name="TC_CARR56" />
     <KeyWord name="TC_CARR57" />
     <KeyWord name="TC_CARR58" />
     <KeyWord name="TC_CARR59" />
     <KeyWord name="TC_CARR6" />
     <KeyWord name="TC_CARR60" />
     <KeyWord name="TC_CARR64" />
     <KeyWord name="TC_CARR65" />
     <KeyWord name="TC_CARR7" />
     <KeyWord name="TC_CARR8" />
     <KeyWord name="TC_CARR9" />
     <KeyWord name="A_TOOLADAPT" />
     <KeyWord name="A_TOOLMTADAPT" />
     <KeyWord name="TC_TP1" />
     <KeyWord name="TC_TP11" />
     <KeyWord name="A_TOOLMTN" />
     <KeyWord name="A_TOOLMTLN" />
     <KeyWord name="TC_TP_MAX_ACC" />
     <KeyWord name="TC_TP_MAX_VELO" />
     <KeyWord name="TC_TP9" />
     <KeyWord name="A_MYMN" />
     <KeyWord name="A_MYMTN" />
     <KeyWord name="A_MYMTLN" />
     <KeyWord name="A_MYMLN" />
     <KeyWord name="TC_TP7" />
     <KeyWord name="TC_TP10" />
     <KeyWord name="TC_TP6" />
     <KeyWord name="TC_TP3" />
     <KeyWord name="TC_TP4" />
     <KeyWord name="TC_TP5" />
     <KeyWord name="TC_TP8" />
     <KeyWord name="A_USEDD" />
     <KeyWord name="A_USEDND" />
     <KeyWord name="A_USEDT" />
     <KeyWord name="TC_TPG5" />
     <KeyWord name="TC_TPG2" />
     <KeyWord name="TC_TPG_DRSPATH" />
     <KeyWord name="TC_TPG_DRSPROG" />
     <KeyWord name="TC_TPG8" />
     <KeyWord name="TC_TPG6" />
     <KeyWord name="TC_TPG7" />
     <KeyWord name="TC_TPG3" />
     <KeyWord name="TC_TPG4" />
     <KeyWord name="TC_TPG9" />
     <KeyWord name="TC_TPG1" />
     <KeyWord name="TC_ISO_*" />
     <KeyWord name="TC_MAP8" />
     <KeyWord name="TC_MAP6" />
     <KeyWord name="TC_MAP7" />
     <KeyWord name="TC_MAP2" />
     <KeyWord name="TC_MAP1" />
     <KeyWord name="TC_MAP4" />
     <KeyWord name="TC_MAP5" />
     <KeyWord name="TC_MAP3" />
     <KeyWord name="TC_MAP10" />
     <KeyWord name="TC_MAP9" />
     <KeyWord name="TC_MAMP1" />
     <KeyWord name="TC_MAMP2" />
     <KeyWord name="TC_MAMP3" />
     <KeyWord name="P_MAGA" />
     <KeyWord name="TC_ADPT_TYPE" />
     <KeyWord name="P_MAGNA" />
     <KeyWord name="TC_DPCEx" />
     <KeyWord name="TC_DPx" />
     <KeyWord name="TC_ECPx" />
     <KeyWord name="TC_SCPx" />
     <KeyWord name="TC_MOPx" />
     <KeyWord name="TC_MPTH" />
     <KeyWord name="TC_TPCx" />
     <KeyWord name="TC_DPCx" />
     <KeyWord name="TC_MAPCx" />
     <KeyWord name="TC_MPPCx" />
     <KeyWord name="TC_MOPCx" />
     <KeyWord name="P_TOOLND" />
     <KeyWord name="P_TOOLNG" />
     <KeyWord name="TC_TP2" />
     <KeyWord name="A_TOOLMN" />
     <KeyWord name="A_TOOLMLN" />
	 <!-- From here insert new stuff -->
	 
	 <!-- From here insert new stuff -->
	 <KeyWord name="HOLES1" func="yes">
           <Overload retVal="REAL" descr="Reference point for row of holes along the 1st axis (abs)">
               <Param name="REAL <SPCA>" />
           </Overload>
		   <Overload retVal="REAL" descr="Reference point for row of holes along the 2nd axis (abs)">
               <Param name="REAL <SPCO>" />
           </Overload>
		   <Overload retVal="REAL" descr="Basic angle of rotation (angle to 1st axis)">
               <Param name="REAL <STA1>" />
           </Overload>
		   <Overload retVal="REAL" descr="Distance from 1st hole to reference point">
               <Param name="REAL <FDIS>" />
           </Overload>
		   <Overload retVal="REAL" descr="Spacing between the holes">
               <Param name="REAL <DBH>" />
           </Overload>
		   <Overload retVal="INT" descr="Number of holes">
               <Param name="INT <NUM>" />
           </Overload>
		   <Overload retVal="INT" descr="Reserved">
               <Param name="INT <_VARI>" />
           </Overload>
		   <Overload retVal="INT" descr="Reserved">
               <Param name="INT <_UMODE>" />
           </Overload>
		   <Overload retVal="STRING[200]" descr="Hidden positions">
               <Param name="STRING[200] <_HIDE>" />
           </Overload>
		   <Overload retVal="INT" descr="Reserved">
               <Param name="INT <_NSP>" />
           </Overload>
		   <Overload retVal="INT" descr="Display mode">
               <Param name="INT <_DMODE>" />
           </Overload>
      </KeyWord>
	  <KeyWord name="HOLES2" func="yes">
           <Overload retVal="REAL"
				descr="HOLES1 - row position pattern

				REAL <SPCA> Reference point for row of holes along the 1th axis (abs)
				REAL <SPCO> Reference point for row of holes along the 2nd axis (abs
				REAL <STA1> Basic angle of rotation (angle to 1st axis)
				REAL <FDIS> Distance from 1st hole to reference point
				REAL <DBH> Spacing between the holes
				INT <NUM> Spacing between the holes
				INT <_VARI> Reserved
				INT <_UMODE> Reserved
				STRING[200] <_HIDE> Hidden positions
				INT <_NSP> Reserved
				INT <_DMODE> Display mode
				">
				<Param name="REAL <SPCA>, REAL <SPCO>, REAL <STA1>, REAL <FDIS>, REAL <DBH>, INT <NUM>, INT <_VARI>, INT <_UMODE>, STRING[200] <_HIDE>, INT <_NSP>, INT <_DMODE>" />
           </Overload>
      </KeyWord>
	  <KeyWord name="HOLES3" func="yes">
           <Overload retVal=""
				descr="HOLES1 - row position pattern

				<SPCA> of REAL - (X0) Reference point for row of holes along the 1th axis (abs)
				<SPCO> of REAL - (Y0) Reference point for row of holes along the 2nd axis (abs
				<STA1> of REAL - (​α0) Basic angle of rotation (angle to 1st axis)
				<FDIS> of REAL - (L0) Distance from 1st hole to reference point
				<DBH> of REAL - (L) Spacing between the holes
				<NUM> of INT - (N) Spacing between the holes
				<_VARI> of INT - Reserved
				<_UMODE> of INT - Reserved
				<_HIDE> of STRING[200] - Hidden positions
				                            Max. 198 characters
​				                            Specification of consecutive position numbers, e.g. 1,3 (positions 1 and 3 are not executed)
				<_NSP> of INT - Reserved
				<_DMODE> of INT - Display mode
				​                    UNITS: ​Machining plane G17/18/19
				​                    0=​ Compatibility, the plane effective before the cycle call remains active
				​                    1=​ G17(only active in the cycle)
				                    ​2=​​ G18(only active in the cycle)
				                    3=​ G19(only active in the cycle)
				">
				<Param name="REAL <SPCA>, REAL <SPCO>, REAL <STA1>, REAL <FDIS>, REAL <DBH>, INT <NUM>, INT <_VARI>, INT <_UMODE>, STRING[200] <_HIDE>, INT <_NSP>, INT <_DMODE>" />
           </Overload>
      </KeyWord>
 </AutoComplete>
</NotepadPlus>
